wagtail_unsplash/__init__.py
wagtail_unsplash/api.py
wagtail_unsplash/models.py
wagtail_unsplash/py.typed
wagtail_unsplash/settings.py
wagtail_unsplash/templates/wagtail_unsplash/results.html
wagtail_unsplash/templates/wagtail_unsplash/search.html
wagtail_unsplash/views/__init__.py
wagtail_unsplash/views/admin.py
wagtail_unsplash/wagtail_hooks.py
wagtail_unsplash-1.0.1.dist-info/LICENCE.txt
wagtail_unsplash-1.0.1.dist-info/METADATA
wagtail_unsplash-1.0.1.dist-info/WHEEL
wagtail_unsplash-1.0.1.dist-info/RECORD
