Metadata-Version: 2.1
Name: wagtail-unsplash
Version: 1.0.1
Summary: Use unsplash.com images in your Wagtail site
License: MIT
Author: Cameron Lamb
Author-email: jafacakes2011@hotmail.co.uk
Requires-Python: >=3.11,<4.0
Classifier: License :: OSI Approved :: MIT License
Classifier: Programming Language :: Python :: 3
Classifier: Programming Language :: Python :: 3.11
Classifier: Programming Language :: Python :: 3.12
Requires-Dist: python-unsplash (>=1.2.5,<2.0.0)
Requires-Dist: queryish (>=0.2,<0.3)
Requires-Dist: wagtail (>5.2,<6.1)
